pidgin_smiley
