Metadata-Version: 1.1
Name: kupfer-plugin-pidgin-smiley
Version: 0.2.2
Summary: Index pidgin smiley theme
Home-page: https://github.com/hugosenari/pidgin_smiley
Author: Hugo Sena Ribeiro
Author-email: hugosenari@gmail.com
License: ISC license
Keywords: kupfer pidgin_smiley
Platform: UNKNOWN
Classifier: Development Status :: 2 - Pre-Alpha
Classifier: Intended Audience :: Developers
Classifier: License :: OSI Approved :: ISC License (ISCL)
Classifier: Natural Language :: English
Classifier: Programming Language :: Python :: 2
Classifier: Programming Language :: Python :: 2.7
Classifier: Programming Language :: Python :: 3
Classifier: Programming Language :: Python :: 3.3
Classifier: Programming Language :: Python :: 3.4
Classifier: Programming Language :: Python :: 3.5
